{
    "eslint.autoFixOnSave": true,
    "eslint.filetypes": ["javascript", "javascriptreact", "typescript", "typescriptreact"],
    "prettier.disableSuccessMessage": true,
    "coc.preferences.formatOnSaveFiletypes": [
        "javascript",
        "javascriptreact",
        "typescript",
        "typescriptreact",
        "rust"
    ],
    "tsserver.formatOnType": true,
    "coc.preferences.formatOnType": true,
    "snippets.ultisnips.pythonPrompt": false,
    "rust-analyzer.rustfmt.rangeFormatting.enable": true,
    "svelte.enable-ts-plugin": true,
    "diagnostic.virtualText": true,
    "diagnostic.virtualTextCurrentLineOnly": false
}
